cosmopy/VERSION.txt
cosmopy/__init__.py
cosmopy/__main__.py
cosmopy/cosmology.py
cosmopy/tests/__init__.py
cosmopy/tests/test_cosmology.py
cosmopy/tests/test_main.py
cosmopy-3.6.dist-info/LICENSE
cosmopy-3.6.dist-info/METADATA
cosmopy-3.6.dist-info/WHEEL
cosmopy-3.6.dist-info/entry_points.txt
cosmopy-3.6.dist-info/top_level.txt
cosmopy-3.6.dist-info/RECORD
