Metadata-Version: 2.1
Name: cosmopy
Version: 3.6
Home-page: https://github.com/lzkelley/cosmopy
Download-URL: https://github.com/lzkelley/cosmopy/archive/v3.6.tar.gz
Author: Luke Zoltan Kelley
Author-email: lzkelley@berkeley.edu
License: MIT
Keywords: utilities,physics,astronomy,cosmology,astrophysics,calculator
Requires-Python: >=3.8
License-File: LICENSE
Requires-Dist: setuptools
Requires-Dist: numpy
Requires-Dist: scipy
Requires-Dist: astropy
Requires-Dist: future
Requires-Dist: click
